<?xml version="1.0" encoding="utf-8" ?>
<dwsync>
<file name="index.html" server="bsd9.quadrahosting.com.au" local="130209855212949000" remote="130235451600000000" Dst="1" />
<file name="mwe_index.html" server="bsd9.quadrahosting.com.au" local="130209855213049000" remote="130235451600000000" Dst="1" />
<file name="gm1.jpg" server="bsd9.quadrahosting.com.au" local="129823434000000000" remote="129823434000000000" Dst="1" />
<file name="gm2.jpg" server="bsd9.quadrahosting.com.au" local="129823434000000000" remote="129823434000000000" Dst="1" />
<file name="gm3.jpg" server="bsd9.quadrahosting.com.au" local="129823434000000000" remote="129823434000000000" Dst="1" />
<file name="gm4.jpg" server="bsd9.quadrahosting.com.au" local="129823434000000000" remote="129823434000000000" Dst="1" />
<file name="gm5.jpg" server="bsd9.quadrahosting.com.au" local="129823434000000000" remote="129823434000000000" Dst="1" />
<file name="gm6.jpg" server="bsd9.quadrahosting.com.au" local="129823434000000000" remote="129823434000000000" Dst="1" />
<file name="gm7.jpg" server="bsd9.quadrahosting.com.au" local="129823434000000000" remote="129823434000000000" Dst="1" />
<file name="P1070070.JPG" server="bsd9.quadrahosting.com.au" local="129823434000000000" remote="129823434000000000" Dst="1" />
<file name="P1070071.JPG" server="bsd9.quadrahosting.com.au" local="129823434000000000" remote="129823434000000000" Dst="1" />
<file name="P1070072_edited-1.JPG" server="bsd9.quadrahosting.com.au" local="129823434000000000" remote="129823434000000000" Dst="1" />
<file name="P1070073.JPG" server="bsd9.quadrahosting.com.au" local="129823434000000000" remote="129823434000000000" Dst="1" />
<file name="P1070074.JPG" server="bsd9.quadrahosting.com.au" local="129823434000000000" remote="129823434000000000" Dst="1" />
<file name="P1070076.JPG" server="bsd9.quadrahosting.com.au" local="129823434000000000" remote="129823434000000000" Dst="1" />
<file name="P1070077.JPG" server="bsd9.quadrahosting.com.au" local="129823434000000000" remote="129823434000000000" Dst="1" />
<file name="P1070079.JPG" server="bsd9.quadrahosting.com.au" local="129823434000000000" remote="129823434000000000" Dst="1" />
<file name="P1070081.JPG" server="bsd9.quadrahosting.com.au" local="129823434000000000" remote="129823434000000000" Dst="1" />
<file name="P1070084.JPG" server="bsd9.quadrahosting.com.au" local="129823434000000000" remote="129823434000000000" Dst="1" />
<file name="P1070086.JPG" server="bsd9.quadrahosting.com.au" local="129823434000000000" remote="129823434000000000" Dst="1" />
<file name="P1070087_edited-1.JPG" server="bsd9.quadrahosting.com.au" local="129823434000000000" remote="129823434000000000" Dst="1" />
</dwsync>